parslet/__init__.py
parslet/cli.py
parslet/main_cli.py
parslet/__pycache__/__init__.cpython-312.pyc
parslet/__pycache__/cli.cpython-312.pyc
parslet/__pycache__/main_cli.cpython-312.pyc
parslet/compat/__init__.py
parslet/compat/dask_adapter.py
parslet/compat/parsl_adapter.py
parslet/core/__init__.py
parslet/core/cache.py
parslet/core/concierge.py
parslet/core/context.py
parslet/core/dag.py
parslet/core/dag_io.py
parslet/core/dask_bridge.py
parslet/core/exporter.py
parslet/core/ir.py
parslet/core/parsl_bridge.py
parslet/core/policy.py
parslet/core/runner.py
parslet/core/scheduler.py
parslet/core/task.py
parslet/core/__pycache__/__init__.cpython-312.pyc
parslet/core/__pycache__/cache.cpython-312.pyc
parslet/core/__pycache__/concierge.cpython-312.pyc
parslet/core/__pycache__/context.cpython-312.pyc
parslet/core/__pycache__/dag.cpython-312.pyc
parslet/core/__pycache__/dag_io.cpython-312.pyc
parslet/core/__pycache__/exporter.cpython-312.pyc
parslet/core/__pycache__/ir.cpython-312.pyc
parslet/core/__pycache__/parsl_bridge.cpython-312.pyc
parslet/core/__pycache__/policy.cpython-312.pyc
parslet/core/__pycache__/runner.cpython-312.pyc
parslet/core/__pycache__/scheduler.cpython-312.pyc
parslet/core/__pycache__/task.cpython-312.pyc
parslet/hybrid/__init__.py
parslet/hybrid/executor.py
parslet/hybrid/relay.py
parslet/plugins/__init__.py
parslet/plugins/loader.py
parslet/plugins/__pycache__/__init__.cpython-312.pyc
parslet/plugins/__pycache__/loader.cpython-312.pyc
parslet/security/__init__.py
parslet/security/defcon.py
parslet/security/__pycache__/__init__.cpython-312.pyc
parslet/security/__pycache__/defcon.cpython-312.pyc
parslet/tasks/__init__.py
parslet/tasks/basic.py
parslet/utils/__init__.py
parslet/utils/checkpointing.py
parslet/utils/diagnostics.py
parslet/utils/network_utils.py
parslet/utils/parslet_defcon.py
parslet/utils/power.py
parslet/utils/resource_utils.py
parslet/utils/__pycache__/__init__.cpython-312.pyc
parslet/utils/__pycache__/checkpointing.cpython-312.pyc
parslet-0.6.2.dist-info/licenses/LICENSE
parslet-0.6.2.dist-info/METADATA
parslet-0.6.2.dist-info/WHEEL
parslet-0.6.2.dist-info/entry_points.txt
parslet-0.6.2.dist-info/top_level.txt
parslet-0.6.2.dist-info/RECORD
