Metadata-Version: 2.4
Name: parslet
Version: 0.6.2
Summary: Simplify Python workflows with a minimal DAG engine.
Author-email: Kelechi Nwankwo <kelechiann.nwankwo@gmail.com>
License-Expression: MIT
Project-URL: Homepage, https://github.com/Kanegraffiti/Parslet
Project-URL: Documentation, https://parslet.readthedocs.io/en/latest/
Project-URL: Source, https://github.com/Kanegraffiti/Parslet
Keywords: workflow,dag,automation
Classifier: Programming Language :: Python :: 3
Classifier: Operating System :: OS Independent
Requires-Python: >=3.11
License-File: LICENSE
Requires-Dist: networkx
Requires-Dist: pillow
Requires-Dist: psutil
Requires-Dist: pydot
Requires-Dist: rich
Provides-Extra: dask
Requires-Dist: dask; extra == "dask"
Provides-Extra: parsl
Requires-Dist: parsl; extra == "parsl"
Provides-Extra: dev
Requires-Dist: black; extra == "dev"
Requires-Dist: ruff; extra == "dev"
Requires-Dist: mypy; extra == "dev"
Requires-Dist: pytest; extra == "dev"
Requires-Dist: build; extra == "dev"
Requires-Dist: twine; extra == "dev"
Dynamic: license-file
